Metadata-Version: 1.0
Name: General-dist
Version: 0.2
Summary: distributions
Home-page: UNKNOWN
Author: Tarun Vignesh
Author-email: tarunvignesh1@gmail.com
License: UNKNOWN
Platform: UNKNOWN
